[
  {
    "original": "https://vitalik.eth.limo/",
    "timestamp": "20210912011827",
    "digest": "5IENPCBX7VKR4THZTQUB45KKYPUNBSZA",
    "mimetype": "text/html",
    "statuscode": "200",
    "wayback_url": "https://web.archive.org/web/20210912011827/https://vitalik.eth.limo/"
  },
  {
    "original": "https://vitalik.eth.limo/",
    "timestamp": "20220122060202",
    "digest": "5VFHZJ6XFZL5KAW3EDJ3ZRNL5IEB5VZM",
    "mimetype": "text/html",
    "statuscode": "200",
    "wayback_url": "https://web.archive.org/web/20220122060202/https://vitalik.eth.limo/"
  },
  {
    "original": "https://vitalik.eth.limo/",
    "timestamp": "20230104190058",
    "digest": "C5H3GNJG6ACQ7LLZU5TMBALXSGQCMAAS",
    "mimetype": "text/html",
    "statuscode": "200",
    "wayback_url": "https://web.archive.org/web/20230104190058/https://vitalik.eth.limo/"
  },
  {
    "original": "https://vitalik.eth.limo/",
    "timestamp": "20240107015008",
    "digest": "2NRBKAACTNQFCDDQI7N66N3AXMVP6KL6",
    "mimetype": "text/html",
    "statuscode": "200",
    "wayback_url": "https://web.archive.org/web/20240107015008/https://vitalik.eth.limo/"
  },
  {
    "original": "https://vitalik.eth.limo/",
    "timestamp": "20250103172504",
    "digest": "ZHZR3TDBLS44KOOEXRABYUFDXTZRHFAL",
    "mimetype": "warc/revisit",
    "statuscode": "-",
    "wayback_url": "https://web.archive.org/web/20250103172504/https://vitalik.eth.limo/"
  },
  {
    "original": "https://vitalik.eth.limo/.well-known/ai-plugin.json",
    "timestamp": "20230609130621",
    "digest": "AA5N4BXG2CXR5AJAFYKL37GFNWCZ2LDL",
    "mimetype": "text/plain",
    "statuscode": "404",
    "wayback_url": "https://web.archive.org/web/20230609130621/https://vitalik.eth.limo/.well-known/ai-plugin.json"
  },
  {
    "original": "https://vitalik.eth.limo/.well-known/ai-plugin.json",
    "timestamp": "20240107015107",
    "digest": "R5H4HDAHRMUQ3RCH2BYBNH6RKSBBFCMP",
    "mimetype": "text/plain",
    "statuscode": "404",
    "wayback_url": "https://web.archive.org/web/20240107015107/https://vitalik.eth.limo/.well-known/ai-plugin.json"
  },
  {
    "original": "https://vitalik.eth.limo/.well-known/ai-plugin.json",
    "timestamp": "20250113135559",
    "digest": "O3VFVN6VM7UUGDB4F6THN5CUQ25EPPI2",
    "mimetype": "text/plain",
    "statuscode": "404",
    "wayback_url": "https://web.archive.org/web/20250113135559/https://vitalik.eth.limo/.well-known/ai-plugin.json"
  },
  {
    "original": "https://vitalik.eth.limo/.well-known/assetlinks.json",
    "timestamp": "20230610025505",
    "digest": "WRLXVUKWNTUDNDIRMNRC6RJTKMEA5DAW",
    "mimetype": "text/plain",
    "statuscode": "404",
    "wayback_url": "https://web.archive.org/web/20230610025505/https://vitalik.eth.limo/.well-known/assetlinks.json"
  },
  {
    "original": "https://vitalik.eth.limo/.well-known/assetlinks.json",
    "timestamp": "20240107015100",
    "digest": "UX3PTUMVN5ZYNOVC2RJVR7Z3IXIRJMMS",
    "mimetype": "text/plain",
    "statuscode": "404",
    "wayback_url": "https://web.archive.org/web/20240107015100/https://vitalik.eth.limo/.well-known/assetlinks.json"
  },
  {
    "original": "https://vitalik.eth.limo/.well-known/assetlinks.json",
    "timestamp": "20250113132103",
    "digest": "JSSWDH4TLYFF2TPMAYYJFQEEIVK4AEMK",
    "mimetype": "text/plain",
    "statuscode": "404",
    "wayback_url": "https://web.archive.org/web/20250113132103/https://vitalik.eth.limo/.well-known/assetlinks.json"
  },
  {
    "original": "https://vitalik.eth.limo/.well-known/dnt-policy.txt",
    "timestamp": "20230609132159",
    "digest": "A6DWV4GVX4T72SHG73AOXQM4II3FBH3I",
    "mimetype": "text/plain",
    "statuscode": "404",
    "wayback_url": "https://web.archive.org/web/20230609132159/https://vitalik.eth.limo/.well-known/dnt-policy.txt"
  },
  {
    "original": "https://vitalik.eth.limo/.well-known/dnt-policy.txt",
    "timestamp": "20240107015211",
    "digest": "ITMA7VKI3CKAIXZ2T3D4UIA6L6AMBUFT",
    "mimetype": "text/plain",
    "statuscode": "404",
    "wayback_url": "https://web.archive.org/web/20240107015211/https://vitalik.eth.limo/.well-known/dnt-policy.txt"
  },
  {
    "original": "https://vitalik.eth.limo/.well-known/dnt-policy.txt",
    "timestamp": "20250113140319",
    "digest": "QR3N5Q7HNYNELHBENZWD55PUBWDRWDXM",
    "mimetype": "text/plain",
    "statuscode": "404",
    "wayback_url": "https://web.archive.org/web/20250113140319/https://vitalik.eth.limo/.well-known/dnt-policy.txt"
  },
  {
    "original": "https://vitalik.eth.limo/.well-known/gpc.json",
    "timestamp": "20230609125841",
    "digest": "VWMHXYLQP4VETTY6FHXSGVT5GNIDQSLD",
    "mimetype": "text/plain",
    "statuscode": "404",
    "wayback_url": "https://web.archive.org/web/20230609125841/https://vitalik.eth.limo/.well-known/gpc.json"
  },
  {
    "original": "https://vitalik.eth.limo/.well-known/gpc.json",
    "timestamp": "20240107015211",
    "digest": "3XUUGA4BYHFZIAMMUNXDAWN7TPBM5XIV",
    "mimetype": "text/plain",
    "statuscode": "404",
    "wayback_url": "https://web.archive.org/web/20240107015211/https://vitalik.eth.limo/.well-known/gpc.json"
  },
  {
    "original": "https://vitalik.eth.limo/.well-known/gpc.json",
    "timestamp": "20250113152750",
    "digest": "YK27PC4YHCLX54MDYVLLED4O2G57TVEM",
    "mimetype": "text/plain",
    "statuscode": "404",
    "wayback_url": "https://web.archive.org/web/20250113152750/https://vitalik.eth.limo/.well-known/gpc.json"
  },
  {
    "original": "https://vitalik.eth.limo/.well-known/nodeinfo",
    "timestamp": "20230609130105",
    "digest": "HLOPGBG32XKCVQTWLO5XWA53HOU3LCXN",
    "mimetype": "text/plain",
    "statuscode": "404",
    "wayback_url": "https://web.archive.org/web/20230609130105/https://vitalik.eth.limo/.well-known/nodeinfo"
  },
  {
    "original": "https://vitalik.eth.limo/.well-known/nodeinfo",
    "timestamp": "20240107015107",
    "digest": "YTZGXWLGOUOHPP2RMBD63O6HD47QXAUL",
    "mimetype": "text/plain",
    "statuscode": "404",
    "wayback_url": "https://web.archive.org/web/20240107015107/https://vitalik.eth.limo/.well-known/nodeinfo"
  },
  {
    "original": "https://vitalik.eth.limo/.well-known/nodeinfo",
    "timestamp": "20250113135315",
    "digest": "NOPGUWUT4X2QKFILJWEFSETXBKMGDZGK",
    "mimetype": "text/plain",
    "statuscode": "404",
    "wayback_url": "https://web.archive.org/web/20250113135315/https://vitalik.eth.limo/.well-known/nodeinfo"
  },
  {
    "original": "https://vitalik.eth.limo/.well-known/openid-configuration",
    "timestamp": "20230609130005",
    "digest": "B7URGGYWQDOZYSF4RINO2HUGTVMVHYZG",
    "mimetype": "text/plain",
    "statuscode": "404",
    "wayback_url": "https://web.archive.org/web/20230609130005/https://vitalik.eth.limo/.well-known/openid-configuration"
  },
  {
    "original": "https://vitalik.eth.limo/.well-known/openid-configuration",
    "timestamp": "20240107015100",
    "digest": "QBD4N6A5ZFULZPPL2L4O2YTAZS4QC6UW",
    "mimetype": "text/plain",
    "statuscode": "404",
    "wayback_url": "https://web.archive.org/web/20240107015100/https://vitalik.eth.limo/.well-known/openid-configuration"
  },
  {
    "original": "https://vitalik.eth.limo/.well-known/openid-configuration",
    "timestamp": "20250113143838",
    "digest": "PMWLDUA7UHFFHTWYQYZQ4V6RK3EXLA2I",
    "mimetype": "text/plain",
    "statuscode": "404",
    "wayback_url": "https://web.archive.org/web/20250113143838/https://vitalik.eth.limo/.well-known/openid-configuration"
  },
  {
    "original": "https://vitalik.eth.limo/.well-known/security.txt",
    "timestamp": "20230609130105",
    "digest": "5Y7HYMCGQI2GZVJTBXB7Q37XJOUTLRAJ",
    "mimetype": "text/plain",
    "statuscode": "404",
    "wayback_url": "https://web.archive.org/web/20230609130105/https://vitalik.eth.limo/.well-known/security.txt"
  },
  {
    "original": "https://vitalik.eth.limo/.well-known/security.txt",
    "timestamp": "20240107015212",
    "digest": "OQMJHIN3O4TVWY3QALLPA35R2LUJY2E6",
    "mimetype": "text/plain",
    "statuscode": "404",
    "wayback_url": "https://web.archive.org/web/20240107015212/https://vitalik.eth.limo/.well-known/security.txt"
  },
  {
    "original": "https://vitalik.eth.limo/.well-known/security.txt",
    "timestamp": "20250113141259",
    "digest": "YOWT5H5G6AKKBZCIQDGKXU2R4CPFDTLK",
    "mimetype": "text/plain",
    "statuscode": "404",
    "wayback_url": "https://web.archive.org/web/20250113141259/https://vitalik.eth.limo/.well-known/security.txt"
  },
  {
    "original": "https://vitalik.eth.limo/.well-known/trust.txt",
    "timestamp": "20230609132235",
    "digest": "IL5NFMSHR5KLRZRVPH7SUVAMYBKH4JJH",
    "mimetype": "text/plain",
    "statuscode": "404",
    "wayback_url": "https://web.archive.org/web/20230609132235/https://vitalik.eth.limo/.well-known/trust.txt"
  },
  {
    "original": "https://vitalik.eth.limo/.well-known/trust.txt",
    "timestamp": "20240107015113",
    "digest": "HUIAPI5MDWDF4K454UV4VMBYN4YLAYQK",
    "mimetype": "text/plain",
    "statuscode": "404",
    "wayback_url": "https://web.archive.org/web/20240107015113/https://vitalik.eth.limo/.well-known/trust.txt"
  },
  {
    "original": "https://vitalik.eth.limo/.well-known/trust.txt",
    "timestamp": "20250113135626",
    "digest": "ALD2F74IHPFFG42JRWOME4VKEOWVNNEJ",
    "mimetype": "text/plain",
    "statuscode": "404",
    "wayback_url": "https://web.archive.org/web/20250113135626/https://vitalik.eth.limo/.well-known/trust.txt"
  },
  {
    "original": "https://vitalik.eth.limo/?ck_subscriber_id=1679907904&utm_source=convertkit&utm_medium=email&utm_campaign=%F0%9F%97%A1%EF%B8%8F%20Ethereum's%20next%20Vision%20-%2015638578",
    "timestamp": "20241214132651",
    "digest": "STI5AK4VKOX7QFAEQMMC5WIBDI4BPKHE",
    "mimetype": "text/html",
    "statuscode": "200",
    "wayback_url": "https://web.archive.org/web/20241214132651/https://vitalik.eth.limo/?ck_subscriber_id=1679907904&utm_source=convertkit&utm_medium=email&utm_campaign=%F0%9F%97%A1%EF%B8%8F%20Ethereum's%20next%20Vision%20-%2015638578"
  },
  {
    "original": "https://vitalik.eth.limo/?guest",
    "timestamp": "20250421214047",
    "digest": "PDPIMSBKDFSWIVS6IUM54YAI3AUJNCHN",
    "mimetype": "text/html",
    "statuscode": "200",
    "wayback_url": "https://web.archive.org/web/20250421214047/https://vitalik.eth.limo/?guest"
  },
  {
    "original": "https://vitalik.eth.limo/?ref=blog.zk.me",
    "timestamp": "20240809002210",
    "digest": "EEWVXBLNVDDMX7U4AD6N5FCTIZAPTF7F",
    "mimetype": "text/html",
    "statuscode": "200",
    "wayback_url": "https://web.archive.org/web/20240809002210/https://vitalik.eth.limo/?ref=blog.zk.me"
  },
  {
    "original": "https://vitalik.eth.limo/?utm_source=globallybased.com&utm_medium=referral&utm_campaign=the-network-state-conference-2024-projects-highlights",
    "timestamp": "20250316152330",
    "digest": "POYMPGAITFCGGFORYV6BL7VC364LEUNP",
    "mimetype": "text/html",
    "statuscode": "200",
    "wayback_url": "https://web.archive.org/web/20250316152330/https://vitalik.eth.limo/?utm_source=globallybased.com&utm_medium=referral&utm_campaign=the-network-state-conference-2024-projects-highlights"
  },
  {
    "original": "https://vitalik.eth.limo/ads.txt",
    "timestamp": "20230609130651",
    "digest": "NBFJS3OSACNPROHVHD5ZQGTQG5RDXPUA",
    "mimetype": "text/plain",
    "statuscode": "404",
    "wayback_url": "https://web.archive.org/web/20230609130651/https://vitalik.eth.limo/ads.txt"
  },
  {
    "original": "https://vitalik.eth.limo/ads.txt",
    "timestamp": "20240107015128",
    "digest": "2SCPBP5SOBISPTTUWPTJX3UYX6UUI7ZH",
    "mimetype": "text/plain",
    "statuscode": "404",
    "wayback_url": "https://web.archive.org/web/20240107015128/https://vitalik.eth.limo/ads.txt"
  },
  {
    "original": "https://vitalik.eth.limo/ads.txt",
    "timestamp": "20250114061449",
    "digest": "RSXDUM5DCB3DUU4UFP3G47HI77M5MTVE",
    "mimetype": "text/plain",
    "statuscode": "404",
    "wayback_url": "https://web.archive.org/web/20250114061449/https://vitalik.eth.limo/ads.txt"
  },
  {
    "original": "https://vitalik.eth.limo/app-ads.txt",
    "timestamp": "20230609130050",
    "digest": "X52NXMNTGGF3EFGZHOOWWZBP4ASEDWYC",
    "mimetype": "text/plain",
    "statuscode": "404",
    "wayback_url": "https://web.archive.org/web/20230609130050/https://vitalik.eth.limo/app-ads.txt"
  },
  {
    "original": "https://vitalik.eth.limo/app-ads.txt",
    "timestamp": "20240107015101",
    "digest": "HXRK3NOJBUC3WY7DZRTS2JILLLGCDX6F",
    "mimetype": "text/plain",
    "statuscode": "404",
    "wayback_url": "https://web.archive.org/web/20240107015101/https://vitalik.eth.limo/app-ads.txt"
  },
  {
    "original": "https://vitalik.eth.limo/app-ads.txt",
    "timestamp": "20250113131938",
    "digest": "NKQHISN3EOHWWSKR5376COY563PUFWGO",
    "mimetype": "text/plain",
    "statuscode": "404",
    "wayback_url": "https://web.archive.org/web/20250113131938/https://vitalik.eth.limo/app-ads.txt"
  },
  {
    "original": "https://vitalik.eth.limo/atom.xml",
    "timestamp": "20241203112233",
    "digest": "3PMKJZ6V4VA47PRKKDOOI6PELWGDIQIY",
    "mimetype": "text/plain",
    "statuscode": "404",
    "wayback_url": "https://web.archive.org/web/20241203112233/https://vitalik.eth.limo/atom.xml"
  },
  {
    "original": "https://vitalik.eth.limo/atom.xml",
    "timestamp": "20250113132107",
    "digest": "R372JEYDH7PF35EV643X3WIEMLVKCNPL",
    "mimetype": "text/plain",
    "statuscode": "404",
    "wayback_url": "https://web.archive.org/web/20250113132107/https://vitalik.eth.limo/atom.xml"
  },
  {
    "original": "https://vitalik.eth.limo/build/19e65b89cee273a249fba4c09b951b74.eot",
    "timestamp": "20220426032130",
    "digest": "UL2REYS5SFLCF3DAIVLPZ3GMJWQTKEUD",
    "mimetype": "text/plain",
    "statuscode": "404",
    "wayback_url": "https://web.archive.org/web/20220426032130/https://vitalik.eth.limo/build/19e65b89cee273a249fba4c09b951b74.eot"
  },
  {
    "original": "https://vitalik.eth.limo/build/19e65b89cee273a249fba4c09b951b74.eot",
    "timestamp": "20230123215308",
    "digest": "THZD2YOLLKDBVEVAE5ELDANWFOOEYPXK",
    "mimetype": "text/plain",
    "statuscode": "404",
    "wayback_url": "https://web.archive.org/web/20230123215308/https://vitalik.eth.limo/build/19e65b89cee273a249fba4c09b951b74.eot"
  },
  {
    "original": "https://vitalik.eth.limo/build/19e65b89cee273a249fba4c09b951b74.eot",
    "timestamp": "20240104133245",
    "digest": "NHNECASZ6BVBRGJ2NR4MNGUIUIAZQNE3",
    "mimetype": "text/html",
    "statuscode": "404",
    "wayback_url": "https://web.archive.org/web/20240104133245/https://vitalik.eth.limo/build/19e65b89cee273a249fba4c09b951b74.eot"
  },
  {
    "original": "https://vitalik.eth.limo/build/19e65b89cee273a249fba4c09b951b74.eot",
    "timestamp": "20250103200603",
    "digest": "CYP64PILUDFJR6KH3EQMNIXLVLSI5ECB",
    "mimetype": "warc/revisit",
    "statuscode": "-",
    "wayback_url": "https://web.archive.org/web/20250103200603/https://vitalik.eth.limo/build/19e65b89cee273a249fba4c09b951b74.eot"
  },
  {
    "original": "https://vitalik.eth.limo/build/260ef443edb4dfd026d82e2b21a4c75c.woff",
    "timestamp": "20220426032132",
    "digest": "KELWQRDZDJZHRAU2TROY4AOYLI6UUFAQ",
    "mimetype": "text/plain",
    "statuscode": "404",
    "wayback_url": "https://web.archive.org/web/20220426032132/https://vitalik.eth.limo/build/260ef443edb4dfd026d82e2b21a4c75c.woff"
  },
  {
    "original": "https://vitalik.eth.limo/build/260ef443edb4dfd026d82e2b21a4c75c.woff",
    "timestamp": "20230123215308",
    "digest": "EMZFQC3N3CH6BBJU2THRK4NKU46IOPT7",
    "mimetype": "text/plain",
    "statuscode": "404",
    "wayback_url": "https://web.archive.org/web/20230123215308/https://vitalik.eth.limo/build/260ef443edb4dfd026d82e2b21a4c75c.woff"
  },
  {
    "original": "https://vitalik.eth.limo/build/260ef443edb4dfd026d82e2b21a4c75c.woff",
    "timestamp": "20240104133246",
    "digest": "MGQF5TQJDUX7NSGAAR7U7AQ4R5OFKTMI",
    "mimetype": "text/html",
    "statuscode": "404",
    "wayback_url": "https://web.archive.org/web/20240104133246/https://vitalik.eth.limo/build/260ef443edb4dfd026d82e2b21a4c75c.woff"
  },
  {
    "original": "https://vitalik.eth.limo/build/260ef443edb4dfd026d82e2b21a4c75c.woff",
    "timestamp": "20250103200604",
    "digest": "F5JZLXHCRKJ2FSZKXFGE7LYJ6MEK7PXT",
    "mimetype": "text/plain",
    "statuscode": "404",
    "wayback_url": "https://web.archive.org/web/20250103200604/https://vitalik.eth.limo/build/260ef443edb4dfd026d82e2b21a4c75c.woff"
  },
  {
    "original": "https://vitalik.eth.limo/build/28df6ee7b407fd8a14b40bc01f4fd3ae.svg",
    "timestamp": "20220426032132",
    "digest": "UXA365GES2POB3AV26K444JJYUEXQMBL",
    "mimetype": "text/plain",
    "statuscode": "404",
    "wayback_url": "https://web.archive.org/web/20220426032132/https://vitalik.eth.limo/build/28df6ee7b407fd8a14b40bc01f4fd3ae.svg"
  },
  {
    "original": "https://vitalik.eth.limo/build/28df6ee7b407fd8a14b40bc01f4fd3ae.svg",
    "timestamp": "20230123215308",
    "digest": "VPWDNEDLCDS2ONPCDYS6QHPJQJDZ4LB4",
    "mimetype": "text/plain",
    "statuscode": "404",
    "wayback_url": "https://web.archive.org/web/20230123215308/https://vitalik.eth.limo/build/28df6ee7b407fd8a14b40bc01f4fd3ae.svg"
  },
  {
    "original": "https://vitalik.eth.limo/build/28df6ee7b407fd8a14b40bc01f4fd3ae.svg",
    "timestamp": "20240104133245",
    "digest": "ZJ5ZWFQHCXVDAA2XBUZG6WZZWVNANHKZ",
    "mimetype": "text/html",
    "statuscode": "404",
    "wayback_url": "https://web.archive.org/web/20240104133245/https://vitalik.eth.limo/build/28df6ee7b407fd8a14b40bc01f4fd3ae.svg"
  },
  {
    "original": "https://vitalik.eth.limo/build/28df6ee7b407fd8a14b40bc01f4fd3ae.svg",
    "timestamp": "20250101090013",
    "digest": "GRWYWCP74G6WFKWD2OEDUCUVQWIOZG5B",
    "mimetype": "warc/revisit",
    "statuscode": "-",
    "wayback_url": "https://web.archive.org/web/20250101090013/https://vitalik.eth.limo/build/28df6ee7b407fd8a14b40bc01f4fd3ae.svg"
  },
  {
    "original": "https://vitalik.eth.limo/build/2c159d0d05473040b53ec79df8797d32.woff",
    "timestamp": "20220426032130",
    "digest": "HBVTFEMM3K5ZVQC7XB7ONW3XJO3VQLMW",
    "mimetype": "text/plain",
    "statuscode": "404",
    "wayback_url": "https://web.archive.org/web/20220426032130/https://vitalik.eth.limo/build/2c159d0d05473040b53ec79df8797d32.woff"
  },
  {
    "original": "https://vitalik.eth.limo/build/2c159d0d05473040b53ec79df8797d32.woff",
    "timestamp": "20230123215309",
    "digest": "DBX6TPMBTI4CPCVZYOGFS42C5LUJRF7B",
    "mimetype": "text/plain",
    "statuscode": "404",
    "wayback_url": "https://web.archive.org/web/20230123215309/https://vitalik.eth.limo/build/2c159d0d05473040b53ec79df8797d32.woff"
  },
  {
    "original": "https://vitalik.eth.limo/build/2c159d0d05473040b53ec79df8797d32.woff",
    "timestamp": "20240104133246",
    "digest": "JEQRQAAIKEQYEULPC3UIDY47S73664ZQ",
    "mimetype": "text/html",
    "statuscode": "404",
    "wayback_url": "https://web.archive.org/web/20240104133246/https://vitalik.eth.limo/build/2c159d0d05473040b53ec79df8797d32.woff"
  },
  {
    "original": "https://vitalik.eth.limo/build/2c159d0d05473040b53ec79df8797d32.woff",
    "timestamp": "20250103200605",
    "digest": "HDOBAVLYPEPJ4QV7GBTQBH34KXXU73F2",
    "mimetype": "warc/revisit",
    "statuscode": "-",
    "wayback_url": "https://web.archive.org/web/20250103200605/https://vitalik.eth.limo/build/2c159d0d05473040b53ec79df8797d32.woff"
  },
  {
    "original": "https://vitalik.eth.limo/build/448c34a56d699c29117adc64c43affeb.woff2",
    "timestamp": "20220426032131",
    "digest": "75LACFZPI2C2CLUPMBRY5VUGYX4VVEMN",
    "mimetype": "text/plain",
    "statuscode": "404",
    "wayback_url": "https://web.archive.org/web/20220426032131/https://vitalik.eth.limo/build/448c34a56d699c29117adc64c43affeb.woff2"
  },
  {
    "original": "https://vitalik.eth.limo/build/448c34a56d699c29117adc64c43affeb.woff2",
    "timestamp": "20230123215309",
    "digest": "ZV53SM2TIQVRIPCFOMOCCKRZ2J2XMRTD",
    "mimetype": "text/plain",
    "statuscode": "404",
    "wayback_url": "https://web.archive.org/web/20230123215309/https://vitalik.eth.limo/build/448c34a56d699c29117adc64c43affeb.woff2"
  },
  {
    "original": "https://vitalik.eth.limo/build/448c34a56d699c29117adc64c43affeb.woff2",
    "timestamp": "20240104133245",
    "digest": "G24NP67RU37O5OT4HKYTZO4UNTYNIRUI",
    "mimetype": "text/html",
    "statuscode": "404",
    "wayback_url": "https://web.archive.org/web/20240104133245/https://vitalik.eth.limo/build/448c34a56d699c29117adc64c43affeb.woff2"
  },
  {
    "original": "https://vitalik.eth.limo/build/448c34a56d699c29117adc64c43affeb.woff2",
    "timestamp": "20250103200603",
    "digest": "PNLHPY4LEPMDRS4FNCXIOJUFGPNF6OB2",
    "mimetype": "warc/revisit",
    "statuscode": "-",
    "wayback_url": "https://web.archive.org/web/20250103200603/https://vitalik.eth.limo/build/448c34a56d699c29117adc64c43affeb.woff2"
  },
  {
    "original": "https://vitalik.eth.limo/build/674f50d287a8c48dc19ba404d20fe713.eot",
    "timestamp": "20220426032129",
    "digest": "JIDU2X52UF443DSNR7KVPIZYVTE5WFJF",
    "mimetype": "text/plain",
    "statuscode": "404",
    "wayback_url": "https://web.archive.org/web/20220426032129/https://vitalik.eth.limo/build/674f50d287a8c48dc19ba404d20fe713.eot"
  },
  {
    "original": "https://vitalik.eth.limo/build/674f50d287a8c48dc19ba404d20fe713.eot",
    "timestamp": "20230123215309",
    "digest": "6PGNFEBCOKYJZOK6YMKF5GCB4YXE5PIZ",
    "mimetype": "text/plain",
    "statuscode": "404",
    "wayback_url": "https://web.archive.org/web/20230123215309/https://vitalik.eth.limo/build/674f50d287a8c48dc19ba404d20fe713.eot"
  },
  {
    "original": "https://vitalik.eth.limo/build/674f50d287a8c48dc19ba404d20fe713.eot",
    "timestamp": "20240104133245",
    "digest": "GSV4B4SGLSDX3LBQ3QVFEC4RRFTKVPG7",
    "mimetype": "text/html",
    "statuscode": "404",
    "wayback_url": "https://web.archive.org/web/20240104133245/https://vitalik.eth.limo/build/674f50d287a8c48dc19ba404d20fe713.eot"
  },
  {
    "original": "https://vitalik.eth.limo/build/674f50d287a8c48dc19ba404d20fe713.eot",
    "timestamp": "20250103200602",
    "digest": "Y5ZARXKFHL5CYD3XYIF42GWXMNIDVNLY",
    "mimetype": "warc/revisit",
    "statuscode": "-",
    "wayback_url": "https://web.archive.org/web/20250103200602/https://vitalik.eth.limo/build/674f50d287a8c48dc19ba404d20fe713.eot"
  },
  {
    "original": "https://vitalik.eth.limo/build/7b3fd4b10ef8298c7df5c5acad4b7e42.eot",
    "timestamp": "20220426032130",
    "digest": "75UXRNQMOBA5EWNB6ZIJW25QPYMIXP2A",
    "mimetype": "text/plain",
    "statuscode": "404",
    "wayback_url": "https://web.archive.org/web/20220426032130/https://vitalik.eth.limo/build/7b3fd4b10ef8298c7df5c5acad4b7e42.eot"
  },
  {
    "original": "https://vitalik.eth.limo/build/7b3fd4b10ef8298c7df5c5acad4b7e42.eot",
    "timestamp": "20230123215309",
    "digest": "FXBF6Q2DOXOBD5D5D656GO3UWT5SDA2W",
    "mimetype": "text/plain",
    "statuscode": "404",
    "wayback_url": "https://web.archive.org/web/20230123215309/https://vitalik.eth.limo/build/7b3fd4b10ef8298c7df5c5acad4b7e42.eot"
  },
  {
    "original": "https://vitalik.eth.limo/build/7b3fd4b10ef8298c7df5c5acad4b7e42.eot",
    "timestamp": "20240104133245",
    "digest": "6E5YXPQWEV5KXJ3R7PXFWEKQEOIERLN3",
    "mimetype": "text/html",
    "statuscode": "404",
    "wayback_url": "https://web.archive.org/web/20240104133245/https://vitalik.eth.limo/build/7b3fd4b10ef8298c7df5c5acad4b7e42.eot"
  },
  {
    "original": "https://vitalik.eth.limo/build/7b3fd4b10ef8298c7df5c5acad4b7e42.eot",
    "timestamp": "20250103200606",
    "digest": "LCY7UKRMI6TTT3OH3QUXU3PEK6H6Z4BC",
    "mimetype": "warc/revisit",
    "statuscode": "-",
    "wayback_url": "https://web.archive.org/web/20250103200606/https://vitalik.eth.limo/build/7b3fd4b10ef8298c7df5c5acad4b7e42.eot"
  },
  {
    "original": "https://vitalik.eth.limo/build/89889688147bd7575d6327160d64e760.svg",
    "timestamp": "20220426032132",
    "digest": "XAGERIY23E6DTKUQK3Q2ETO3N5NBYRFT",
    "mimetype": "text/plain",
    "statuscode": "404",
    "wayback_url": "https://web.archive.org/web/20220426032132/https://vitalik.eth.limo/build/89889688147bd7575d6327160d64e760.svg"
  },
  {
    "original": "https://vitalik.eth.limo/build/89889688147bd7575d6327160d64e760.svg",
    "timestamp": "20230123215308",
    "digest": "C2YMVF67K6ACURGLAQHPPHWJI74E7MSB",
    "mimetype": "text/plain",
    "statuscode": "404",
    "wayback_url": "https://web.archive.org/web/20230123215308/https://vitalik.eth.limo/build/89889688147bd7575d6327160d64e760.svg"
  },
  {
    "original": "https://vitalik.eth.limo/build/89889688147bd7575d6327160d64e760.svg",
    "timestamp": "20240104133245",
    "digest": "7EWFO5CIJLGU5HYPOI5NNQWEDS2LQKD7",
    "mimetype": "text/html",
    "statuscode": "404",
    "wayback_url": "https://web.archive.org/web/20240104133245/https://vitalik.eth.limo/build/89889688147bd7575d6327160d64e760.svg"
  },
  {
    "original": "https://vitalik.eth.limo/build/89889688147bd7575d6327160d64e760.svg",
    "timestamp": "20250103200604",
    "digest": "TMKCWWTNCWOI4CLENKH4Y74BSMQCTQG6",
    "mimetype": "warc/revisit",
    "statuscode": "-",
    "wayback_url": "https://web.archive.org/web/20250103200604/https://vitalik.eth.limo/build/89889688147bd7575d6327160d64e760.svg"
  },
  {
    "original": "https://vitalik.eth.limo/build/912ec66d7572ff821749319396470bde.svg",
    "timestamp": "20220426032129",
    "digest": "7FDHWGE3XUXR54SHUH4HYHO6KIB5XVHM",
    "mimetype": "text/plain",
    "statuscode": "404",
    "wayback_url": "https://web.archive.org/web/20220426032129/https://vitalik.eth.limo/build/912ec66d7572ff821749319396470bde.svg"
  },
  {
    "original": "https://vitalik.eth.limo/build/912ec66d7572ff821749319396470bde.svg",
    "timestamp": "20230123215309",
    "digest": "CW3O3LZK64W7WQQ2RPR6MOYH5HVY67VK",
    "mimetype": "text/plain",
    "statuscode": "404",
    "wayback_url": "https://web.archive.org/web/20230123215309/https://vitalik.eth.limo/build/912ec66d7572ff821749319396470bde.svg"
  },
  {
    "original": "https://vitalik.eth.limo/build/912ec66d7572ff821749319396470bde.svg",
    "timestamp": "20240104133245",
    "digest": "Y5YPNWNJDKRXNXZPB3FWLQDNRATKAT4H",
    "mimetype": "text/html",
    "statuscode": "404",
    "wayback_url": "https://web.archive.org/web/20240104133245/https://vitalik.eth.limo/build/912ec66d7572ff821749319396470bde.svg"
  },
  {
    "original": "https://vitalik.eth.limo/build/912ec66d7572ff821749319396470bde.svg",
    "timestamp": "20250103200601",
    "digest": "WDDB4SFSFOPYXTCPRLCSHF2DXMJWLNKA",
    "mimetype": "warc/revisit",
    "statuscode": "-",
    "wayback_url": "https://web.archive.org/web/20250103200601/https://vitalik.eth.limo/build/912ec66d7572ff821749319396470bde.svg"
  },
  {
    "original": "https://vitalik.eth.limo/build/9e5cc6ea569143be7be53e6f6c7bcebf.svg",
    "timestamp": "20220426032132",
    "digest": "6X5QNOALYE7ZORMNWR6FXAAYOQ7XVE5C",
    "mimetype": "text/plain",
    "statuscode": "404",
    "wayback_url": "https://web.archive.org/web/20220426032132/https://vitalik.eth.limo/build/9e5cc6ea569143be7be53e6f6c7bcebf.svg"
  },
  {
    "original": "https://vitalik.eth.limo/build/9e5cc6ea569143be7be53e6f6c7bcebf.svg",
    "timestamp": "20230123215308",
    "digest": "QXPIPHHOA6RTTAM6BKF6SW3QL4SM4AYC",
    "mimetype": "text/plain",
    "statuscode": "404",
    "wayback_url": "https://web.archive.org/web/20230123215308/https://vitalik.eth.limo/build/9e5cc6ea569143be7be53e6f6c7bcebf.svg"
  },
  {
    "original": "https://vitalik.eth.limo/build/9e5cc6ea569143be7be53e6f6c7bcebf.svg",
    "timestamp": "20240104133246",
    "digest": "NSLGZJWT5WMC5JNRBZILOJJHOEU7G6UE",
    "mimetype": "text/html",
    "statuscode": "404",
    "wayback_url": "https://web.archive.org/web/20240104133246/https://vitalik.eth.limo/build/9e5cc6ea569143be7be53e6f6c7bcebf.svg"
  },
  {
    "original": "https://vitalik.eth.limo/build/9e5cc6ea569143be7be53e6f6c7bcebf.svg",
    "timestamp": "20250103200605",
    "digest": "6QRKTJEU2BRUFFPNGDDAG76U722GBXBD",
    "mimetype": "text/plain",
    "statuscode": "404",
    "wayback_url": "https://web.archive.org/web/20250103200605/https://vitalik.eth.limo/build/9e5cc6ea569143be7be53e6f6c7bcebf.svg"
  },
  {
    "original": "https://vitalik.eth.limo/build/af7ae505a9eed503f8b8e6982036873e.woff2",
    "timestamp": "20220426032129",
    "digest": "UEG2ZIW6ML3H6GRE4HGOKGPTUF5HE57K",
    "mimetype": "text/plain",
    "statuscode": "404",
    "wayback_url": "https://web.archive.org/web/20220426032129/https://vitalik.eth.limo/build/af7ae505a9eed503f8b8e6982036873e.woff2"
  },
  {
    "original": "https://vitalik.eth.limo/build/af7ae505a9eed503f8b8e6982036873e.woff2",
    "timestamp": "20230123215308",
    "digest": "U6T2OEREXIMNHNWP2DAIMJBKMN76IKV2",
    "mimetype": "text/plain",
    "statuscode": "404",
    "wayback_url": "https://web.archive.org/web/20230123215308/https://vitalik.eth.limo/build/af7ae505a9eed503f8b8e6982036873e.woff2"
  },
  {
    "original": "https://vitalik.eth.limo/build/af7ae505a9eed503f8b8e6982036873e.woff2",
    "timestamp": "20240104133245",
    "digest": "TUG4RQVIZV5WWIAH4YQTFOXC5OKW5A6R",
    "mimetype": "text/html",
    "statuscode": "404",
    "wayback_url": "https://web.archive.org/web/20240104133245/https://vitalik.eth.limo/build/af7ae505a9eed503f8b8e6982036873e.woff2"
  },
  {
    "original": "https://vitalik.eth.limo/build/af7ae505a9eed503f8b8e6982036873e.woff2",
    "timestamp": "20250103200602",
    "digest": "X6XWXXY2GVK6W4ZJZNUJHME3I4TOXZVE",
    "mimetype": "warc/revisit",
    "statuscode": "-",
    "wayback_url": "https://web.archive.org/web/20250103200602/https://vitalik.eth.limo/build/af7ae505a9eed503f8b8e6982036873e.woff2"
  },
  {
    "original": "https://vitalik.eth.limo/build/b06871f281fee6b241d60582ae9369b9.ttf",
    "timestamp": "20220426032129",
    "digest": "SKBM5T476B6FTLCQK2LFJVA5L3ANI6CJ",
    "mimetype": "text/plain",
    "statuscode": "404",
    "wayback_url": "https://web.archive.org/web/20220426032129/https://vitalik.eth.limo/build/b06871f281fee6b241d60582ae9369b9.ttf"
  },
  {
    "original": "https://vitalik.eth.limo/build/b06871f281fee6b241d60582ae9369b9.ttf",
    "timestamp": "20230123215308",
    "digest": "JX6CINI4OQTA4P7WDTDAJSY2JQ2TPGRD",
    "mimetype": "text/plain",
    "statuscode": "404",
    "wayback_url": "https://web.archive.org/web/20230123215308/https://vitalik.eth.limo/build/b06871f281fee6b241d60582ae9369b9.ttf"
  },
  {
    "original": "https://vitalik.eth.limo/build/b06871f281fee6b241d60582ae9369b9.ttf",
    "timestamp": "20240104133245",
    "digest": "LJUCPDGA5MASEPXA7FNNCWFVSZDPYVPX",
    "mimetype": "text/html",
    "statuscode": "404",
    "wayback_url": "https://web.archive.org/web/20240104133245/https://vitalik.eth.limo/build/b06871f281fee6b241d60582ae9369b9.ttf"
  },
  {
    "original": "https://vitalik.eth.limo/build/b06871f281fee6b241d60582ae9369b9.ttf",
    "timestamp": "20250103200601",
    "digest": "5UOME72T2DA7CMBP2JT6VTZWGGW2K2HO",
    "mimetype": "warc/revisit",
    "statuscode": "-",
    "wayback_url": "https://web.archive.org/web/20250103200601/https://vitalik.eth.limo/build/b06871f281fee6b241d60582ae9369b9.ttf"
  },
  {
    "original": "https://vitalik.eth.limo/build/dd4781d1acc57ba4c4808d1b44301201.ttf",
    "timestamp": "20220426032130",
    "digest": "45GCUXQMQZYJTQNKERP7XE65IQIHHCQW",
    "mimetype": "text/plain",
    "statuscode": "404",
    "wayback_url": "https://web.archive.org/web/20220426032130/https://vitalik.eth.limo/build/dd4781d1acc57ba4c4808d1b44301201.ttf"
  },
  {
    "original": "https://vitalik.eth.limo/build/dd4781d1acc57ba4c4808d1b44301201.ttf",
    "timestamp": "20230123215309",
    "digest": "E4OY4GPFDTJM3KVITJ25GIAPUA4XRLC2",
    "mimetype": "text/plain",
    "statuscode": "404",
    "wayback_url": "https://web.archive.org/web/20230123215309/https://vitalik.eth.limo/build/dd4781d1acc57ba4c4808d1b44301201.ttf"
  },
  {
    "original": "https://vitalik.eth.limo/build/dd4781d1acc57ba4c4808d1b44301201.ttf",
    "timestamp": "20240104133245",
    "digest": "RFJ3QGYJKC6VZHY7U4ENSI23XCYPP35G",
    "mimetype": "text/html",
    "statuscode": "404",
    "wayback_url": "https://web.archive.org/web/20240104133245/https://vitalik.eth.limo/build/dd4781d1acc57ba4c4808d1b44301201.ttf"
  },
  {
    "original": "https://vitalik.eth.limo/build/dd4781d1acc57ba4c4808d1b44301201.ttf",
    "timestamp": "20250103200603",
    "digest": "UJZQZRW5EYZUZ6ITTY54TOTBYN2UXLYE",
    "mimetype": "warc/revisit",
    "statuscode": "-",
    "wayback_url": "https://web.archive.org/web/20250103200603/https://vitalik.eth.limo/build/dd4781d1acc57ba4c4808d1b44301201.ttf"
  },
  {
    "original": "https://vitalik.eth.limo/build/e18bbf611f2a2e43afc071aa2f4e1512.ttf",
    "timestamp": "20220426032132",
    "digest": "Z7VPXO3K4FFWT5XVGH5KBYF2DGGSL7OX",
    "mimetype": "text/plain",
    "statuscode": "404",
    "wayback_url": "https://web.archive.org/web/20220426032132/https://vitalik.eth.limo/build/e18bbf611f2a2e43afc071aa2f4e1512.ttf"
  },
  {
    "original": "https://vitalik.eth.limo/build/e18bbf611f2a2e43afc071aa2f4e1512.ttf",
    "timestamp": "20230123215309",
    "digest": "46FIJBX4BG374LZZBQXLKARM4PVPRHZL",
    "mimetype": "text/plain",
    "statuscode": "404",
    "wayback_url": "https://web.archive.org/web/20230123215309/https://vitalik.eth.limo/build/e18bbf611f2a2e43afc071aa2f4e1512.ttf"
  },
  {
    "original": "https://vitalik.eth.limo/build/e18bbf611f2a2e43afc071aa2f4e1512.ttf",
    "timestamp": "20240104133245",
    "digest": "CQWW66GOTWTQDHSLSHQJFONSHABWBBCE",
    "mimetype": "text/html",
    "statuscode": "404",
    "wayback_url": "https://web.archive.org/web/20240104133245/https://vitalik.eth.limo/build/e18bbf611f2a2e43afc071aa2f4e1512.ttf"
  },
  {
    "original": "https://vitalik.eth.limo/build/e18bbf611f2a2e43afc071aa2f4e1512.ttf",
    "timestamp": "20250103200605",
    "digest": "F3WOXBXDENAI55PCJ4R6U3PMKOXXUO7Z",
    "mimetype": "warc/revisit",
    "statuscode": "-",
    "wayback_url": "https://web.archive.org/web/20250103200605/https://vitalik.eth.limo/build/e18bbf611f2a2e43afc071aa2f4e1512.ttf"
  },
  {
    "original": "https://vitalik.eth.limo/build/ed294b221e32c83d9e79195d599313d3.ttf",
    "timestamp": "20220426032131",
    "digest": "VAUUVIBDNTMWAX45A73SUI7575LJCPBG",
    "mimetype": "text/plain",
    "statuscode": "404",
    "wayback_url": "https://web.archive.org/web/20220426032131/https://vitalik.eth.limo/build/ed294b221e32c83d9e79195d599313d3.ttf"
  },
  {
    "original": "https://vitalik.eth.limo/build/ed294b221e32c83d9e79195d599313d3.ttf",
    "timestamp": "20230123215308",
    "digest": "NZFRDCFPNDDAOU47V6UT6TUEMFWGWV5Y",
    "mimetype": "text/plain",
    "statuscode": "404",
    "wayback_url": "https://web.archive.org/web/20230123215308/https://vitalik.eth.limo/build/ed294b221e32c83d9e79195d599313d3.ttf"
  },
  {
    "original": "https://vitalik.eth.limo/build/ed294b221e32c83d9e79195d599313d3.ttf",
    "timestamp": "20240104133246",
    "digest": "OZVH45UXZSUQ6Y7D7DQEIESSB3KJZXUJ",
    "mimetype": "text/html",
    "statuscode": "404",
    "wayback_url": "https://web.archive.org/web/20240104133246/https://vitalik.eth.limo/build/ed294b221e32c83d9e79195d599313d3.ttf"
  }
]